flask_bower/__init__.py
Flask_Bower-2.0.0.dist-info/LICENSE.md
Flask_Bower-2.0.0.dist-info/METADATA
Flask_Bower-2.0.0.dist-info/WHEEL
Flask_Bower-2.0.0.dist-info/top_level.txt
Flask_Bower-2.0.0.dist-info/RECORD
