Metadata-Version: 2.1
Name: Flask-Bower
Version: 2.0.0
Summary: An extension to manage and serve your javascript assets with bower
Author-email: Christian Becker <christian@dabecka.de>
License: GNU GENERAL PUBLIC LICENSE
Project-URL: Homepage, http://github.com/lobeck/flask-bower
Classifier: Environment :: Web Environment
Classifier: Intended Audience :: Developers
Classifier: License :: OSI Approved :: GNU General Public License v2 (GPLv2)
Classifier: Operating System :: OS Independent
Classifier: Programming Language :: Python
Classifier: Programming Language :: Python :: 3
Classifier: Topic :: Internet :: WWW/HTTP :: Dynamic Content
Classifier: Topic :: Software Development :: Libraries :: Python Modules
Requires-Python: >3.0
License-File: LICENSE.md
Requires-Dist: Flask >=0.9
